{
  "mods": [
    {
      "name": "trello-importer",
      "friendly-name": "Trello Importer",
      "description": "Import your Trello lists and cards into Mangose",
      "version": "1.0",
      "license": "MIT",
      "author": "Mangose"
    },
    {
      "name": "quick-task-importer",
      "friendly-name": "Quick Task Importer",
      "description": "Paste a comma or line-separated list to instantly create tasks in Mangose",
      "version": "1.0",
      "license": "MIT",
      "author": "Mangose"
    },
    {
      "name": "pk-dex",
      "friendly-name": "Pokedex",
      "description": "Find Pokemon in Mangose",
      "version": "1.0",
      "license": "MIT",
      "author": "Mangose"
    }
  ]
}
